eldl/__about__.py
eldl/__init__.py
eldl/__main__.py
eldl/py.typed
eldl-0.0.1a1.dist-info/METADATA
eldl-0.0.1a1.dist-info/WHEEL
eldl-0.0.1a1.dist-info/licenses/LICENSE
eldl-0.0.1a1.dist-info/RECORD
